{
    "document_name": "ngua-hau-mon.json",
    "document_name_accent": "ngua hau mon.json",
    "document_title": "What disease is anal itching? Causes, symptoms and prevention",
    "document_category": "Gastrointestinal - Hepatobiliary",
    "subsection_name": "ngua-hau-mon.json_6_Frequently asked questions about anal itching",
    "subsection_content": "1. Is anal itching dangerous?\nIn many cases, anal itching is not dangerous and can be effectively improved by regular hygiene, changing eating and living habits and using medication. However, after a while, if the symptoms do not improve or even become worse, the patient should proactively contact a doctor for timely monitoring and diagnosis. Some worrying accompanying signs include:\nThe anus and surrounding area have pus discharge; Diarrhea with blood; Hemorrhoids protruding; The skin around the anus is dull and abnormally thick.\n2. Is it okay to have anal itching after going to the toilet?\nAnal itching after defecation often comes from the following two causes:\nThe anus is not cleaned thoroughly: After defecation, if not cleaned thoroughly, the remaining waste will cause an uncomfortable burning sensation; The anus is not cleaned thoroughly: After defecation, if not cleaned thoroughly, the remaining waste will cause an uncomfortable burning sensation.\nCleaning the anus too vigorously: Rubbing the anus too vigorously after defecation can lead to irritation and itching.; Cleaning the anus too vigorously: Rubbing the anus too vigorously after defecation can lead to irritation and itching.\nAt this time, changing habits can bring positive improvements. However, if this symptom continues to repeat and becomes more severe, the patient should consult a doctor to detect other medical problems early.\n3. Does having anal itching at night mean you have a disease?\nPinworms can cause irritation, making the area around the anus itchy. This type of parasite tends to be more active at night, so this is the time when the itching feeling is most intense.\n4. Does anal itching mean hemorrhoids?\nHemorrhoids are one of the common causes of anal itching. However, this is not the only factor. This symptom can also be caused by improper hygiene habits, eating habits, sexual diseases, pinworm infection... In this case, the patient can contact a doctor early for an accurate diagnosis.\n5. Is it okay to have anal itching during pregnancy?\nDuring pregnancy, women are likely to experience anal itching because hormones cause veins to dilate. In this case, the patient should discuss carefully with the doctor to have appropriate treatment methods. Do not arbitrarily use medication to avoid affecting health as well as the fetus.\nCenter for Gastrointestinal Endoscopy and Surgery (Tam Anh General Hospital, Ho Chi Minh City) and Department of Gastroenterology - Hepatobiliary - Pancreatic (Tam Anh General Hospital, Hanoi) are prestigious medical centers specializing in Gastroenterology, providing High-class, effective examination and treatment services for patients with mild to severe liver problems (fatty liver, acute and chronic hepatitis, cirrhosis, liver cancer...). Tam Anh General Hospital system brings together a team of highly specialized and experienced Internal Medicine - Surgery - Gastrointestinal Endoscopy doctors, in addition to the support of a modern medical equipment system imported from abroad. in addition, serving the maximum examination and treatment needs of customers.\nTo schedule an examination and treatment of liver diseases with gastroenterology specialists of Tam Anh General Hospital System, please contact:\nAbove is a summary of all information related to common anal itching. Hopefully with these shares, patients will have more useful updates to proactively prevent, monitor and treat effectively.",
    "subsection_title": "ngua hau mon.json. Frequently asked questions about anal itching",
    "subsection_data": "ngua hau mon.json. Frequently asked questions about anal itching\n1. Is anal itching dangerous?\nIn many cases, anal itching is not dangerous and can be effectively improved by regular hygiene, changing eating and living habits and using medication. However, after a while, if the symptoms do not improve or even become worse, the patient should proactively contact a doctor for timely monitoring and diagnosis. Some worrying accompanying signs include:\nThe anus and surrounding area have pus discharge; Diarrhea with blood; Hemorrhoids protruding; The skin around the anus is dull and abnormally thick.\n2. Is it okay to have anal itching after going to the toilet?\nAnal itching after defecation often comes from the following two causes:\nThe anus is not cleaned thoroughly: After defecation, if not cleaned thoroughly, the remaining waste will cause an uncomfortable burning sensation; The anus is not cleaned thoroughly: After defecation, if not cleaned thoroughly, the remaining waste will cause an uncomfortable burning sensation.\nCleaning the anus too vigorously: Rubbing the anus too vigorously after defecation can lead to irritation and itching.; Cleaning the anus too vigorously: Rubbing the anus too vigorously after defecation can lead to irritation and itching.\nAt this time, changing habits can bring positive improvements. However, if this symptom continues to repeat and becomes more severe, the patient should consult a doctor to detect other medical problems early.\n3. Does having anal itching at night mean you have a disease?\nPinworms can cause irritation, making the area around the anus itchy. This type of parasite tends to be more active at night, so this is the time when the itching feeling is most intense.\n4. Does anal itching mean hemorrhoids?\nHemorrhoids are one of the common causes of anal itching. However, this is not the only factor. This symptom can also be caused by improper hygiene habits, eating habits, sexual diseases, pinworm infection... In this case, the patient can contact a doctor early for an accurate diagnosis.\n5. Is it okay to have anal itching during pregnancy?\nDuring pregnancy, women are likely to experience anal itching because hormones cause veins to dilate. In this case, the patient should discuss carefully with the doctor to have appropriate treatment methods. Do not arbitrarily use medication to avoid affecting health as well as the fetus.\nCenter for Gastrointestinal Endoscopy and Surgery (Tam Anh General Hospital, Ho Chi Minh City) and Department of Gastroenterology - Hepatobiliary - Pancreatic (Tam Anh General Hospital, Hanoi) are prestigious medical centers specializing in Gastroenterology, providing High-class, effective examination and treatment services for patients with mild to severe liver problems (fatty liver, acute and chronic hepatitis, cirrhosis, liver cancer...). Tam Anh General Hospital system brings together a team of highly specialized and experienced Internal Medicine - Surgery - Gastrointestinal Endoscopy doctors, in addition to the support of a modern medical equipment system imported from abroad. in addition, serving the maximum examination and treatment needs of customers.\nTo schedule an examination and treatment of liver diseases with gastroenterology specialists of Tam Anh General Hospital System, please contact:\nAbove is a summary of all information related to common anal itching. Hopefully with these shares, patients will have more useful updates to proactively prevent, monitor and treat effectively."
}