{
    "document_name": "roi-loan-giong-noi.json",
    "document_name_accent": "roi loan giong noi.json",
    "document_title": "Voice disorders: Causes, signs and treatments",
    "document_category": "Ear, nose and throat",
    "subsection_name": "roi-loan-giong-noi.json_0_What is a voice disorder?",
    "subsection_content": "Voice Disorders or Dysphonia is a condition that causes the patient's voice to change differently than before. When experiencing this condition, the patient may notice changes in one or more voice characteristics, such as disturbances in frequency, intensity, timbre or voice quality.",
    "subsection_title": "roi loan giong noi.json. What is a voice disorder?",
    "subsection_data": "roi loan giong noi.json. What is a voice disorder?\nVoice Disorders or Dysphonia is a condition that causes the patient's voice to change differently than before. When experiencing this condition, the patient may notice changes in one or more voice characteristics, such as disturbances in frequency, intensity, timbre or voice quality."
}