{
    "document_name": "roi-loan-tieu-hoa.json",
    "document_name_accent": "roi loan tieu hoa.json",
    "document_title": "Digestive disorders: Causes, symptoms and prevention",
    "document_category": "Gastrointestinal - Hepatobiliary",
    "subsection_name": "roi-loan-tieu-hoa.json_9_If you have digestive disorders, what should you eat and what should you avoid?",
    "subsection_content": "Diet has a great influence on the treatment, care and recovery of digestive disorders. Food groups that should be eaten and avoided include:\nFoods to eat: Vegetables, grains, nuts, beans, ginger, yogurt...; Foods to avoid: Spicy foods, lots of acid, milk and dairy products, alcohol...\nCenter for Gastrointestinal Endoscopy and Surgery (Tam Anh General Hospital, Ho Chi Minh City) and Department of Gastroenterology - Hepatobiliary - Pancreatic (Tam Anh General Hospital, Hanoi) are prestigious medical centers specializing in Gastroenterology, providing High-class, effective examination and treatment services for patients with mild to severe liver problems (fatty liver, acute and chronic hepatitis, cirrhosis, liver cancer...). Tam Anh General Hospital system brings together a team of highly specialized and experienced Internal Medicine - Surgery - Gastrointestinal Endoscopy doctors, in addition to the support of a modern medical equipment system imported from abroad. in addition, serving the maximum examination and treatment needs of customers.\nTo schedule an examination and treatment of liver diseases with gastroenterology specialists of Tam Anh General Hospital System, please contact:\nAbove is a summary of all detailed information related to digestive disorders. Hopefully with these shares, patients will have more useful updates to proactively prevent, monitor, detect and treat early, to minimize dangerous complications.",
    "subsection_title": "roi loan tieu hoa.json. If you have digestive disorders, what should you eat and what should you avoid?",
    "subsection_data": "roi loan tieu hoa.json. If you have digestive disorders, what should you eat and what should you avoid?\nDiet has a great influence on the treatment, care and recovery of digestive disorders. Food groups that should be eaten and avoided include:\nFoods to eat: Vegetables, grains, nuts, beans, ginger, yogurt...; Foods to avoid: Spicy foods, lots of acid, milk and dairy products, alcohol...\nCenter for Gastrointestinal Endoscopy and Surgery (Tam Anh General Hospital, Ho Chi Minh City) and Department of Gastroenterology - Hepatobiliary - Pancreatic (Tam Anh General Hospital, Hanoi) are prestigious medical centers specializing in Gastroenterology, providing High-class, effective examination and treatment services for patients with mild to severe liver problems (fatty liver, acute and chronic hepatitis, cirrhosis, liver cancer...). Tam Anh General Hospital system brings together a team of highly specialized and experienced Internal Medicine - Surgery - Gastrointestinal Endoscopy doctors, in addition to the support of a modern medical equipment system imported from abroad. in addition, serving the maximum examination and treatment needs of customers.\nTo schedule an examination and treatment of liver diseases with gastroenterology specialists of Tam Anh General Hospital System, please contact:\nAbove is a summary of all detailed information related to digestive disorders. Hopefully with these shares, patients will have more useful updates to proactively prevent, monitor, detect and treat early, to minimize dangerous complications."
}