{
    "document_name": "sui-mao-ga.json",
    "document_name_accent": "sui mao ga.json",
    "document_title": "Genital warts: Causes, signs, complications, prevention",
    "document_category": "Andrology",
    "subsection_name": "sui-mao-ga.json_0_What is genital warts?",
    "subsection_content": "Genital warts, or genital warts, are a common sexually transmitted disease caused by a virus, manifested by soft warts on the genitals accompanied by pain and itching. snoring, discomfort. The virus that causes genital warts is Human Papillomavirus (HPV). (first)\nSome people develop genital warts within a few weeks of infection, but in others it can take months or years. In fact, most cases of HPV infection are asymptomatic or undetected. The proportion of people with obvious symptoms is very low, only about 1-2% of cases. Therefore, it is difficult for patients to determine their condition and accidentally transmit the virus to others.",
    "subsection_title": "sui mao ga.json. What is genital warts?",
    "subsection_data": "sui mao ga.json. What is genital warts?\nGenital warts, or genital warts, are a common sexually transmitted disease caused by a virus, manifested by soft warts on the genitals accompanied by pain and itching. snoring, discomfort. The virus that causes genital warts is Human Papillomavirus (HPV). (first)\nSome people develop genital warts within a few weeks of infection, but in others it can take months or years. In fact, most cases of HPV infection are asymptomatic or undetected. The proportion of people with obvious symptoms is very low, only about 1-2% of cases. Therefore, it is difficult for patients to determine their condition and accidentally transmit the virus to others."
}