{
    "document_name": "thieu-mau-co-tim.json",
    "document_name_accent": "thieu mau co tim.json",
    "document_title": "Myocardial ischemia: Causes, signs, complications and prevention",
    "document_category": "Heart vascular",
    "subsection_name": "thieu-mau-co-tim.json_1_Signs of myocardial ischemia",
    "subsection_content": "Common symptoms\nThe most common and typical symptom of this disease is angina (especially in the left chest) (2). However, in some cases, patients do not have any signs or symptoms (this condition is also known as silent myocardial ischemia). Additionally, women, the elderly, or people with diabetes may experience signs including:\nFast heart beat; Shortness of breath during exercise or physical activity; Nausea and vomiting; Neck or jaw pain; Shoulder or arm pain; Sweat; Tired\nHeart palpitations, left chest pain, and sweating are signs of anemic heart muscle\nSevere symptoms\nIn some cases, if not treated promptly, ischemic cardiomyopathy can threaten the patient's life. Therefore, when any of the following signs appear, patients need to immediately go to a medical facility for timely treatment:\nSevere chest pain or persistent chest pain that does not go away; Skin is rough; Nausea or vomiting; Rapid breathing, rapid breathing; Shoulder pain or arm pain",
    "subsection_title": "thieu mau co tim.json. Signs of myocardial ischemia",
    "subsection_data": "thieu mau co tim.json. Signs of myocardial ischemia\nCommon symptoms\nThe most common and typical symptom of this disease is angina (especially in the left chest) (2). However, in some cases, patients do not have any signs or symptoms (this condition is also known as silent myocardial ischemia). Additionally, women, the elderly, or people with diabetes may experience signs including:\nFast heart beat; Shortness of breath during exercise or physical activity; Nausea and vomiting; Neck or jaw pain; Shoulder or arm pain; Sweat; Tired\nHeart palpitations, left chest pain, and sweating are signs of anemic heart muscle\nSevere symptoms\nIn some cases, if not treated promptly, ischemic cardiomyopathy can threaten the patient's life. Therefore, when any of the following signs appear, patients need to immediately go to a medical facility for timely treatment:\nSevere chest pain or persistent chest pain that does not go away; Skin is rough; Nausea or vomiting; Rapid breathing, rapid breathing; Shoulder pain or arm pain"
}