{
    "document_name": "tieu-dem.json",
    "document_name_accent": "tieu dem.json",
    "document_title": "Nocturia: Causes, signs and prevention",
    "document_category": "Urology",
    "subsection_name": "tieu-dem.json_1_Symptoms of nocturia",
    "subsection_content": "A normal person can sleep 6-8 hours, without waking up in the middle of the night to urinate. People with nocturia will wake up more than once during sleep to urinate. If this condition lasts long, it can make the patient feel tired or even physically weak. When the cause comes from a disease, if you delay treatment, you can face dangerous complications from the disease.",
    "subsection_title": "tieu dem.json. Symptoms of nocturia",
    "subsection_data": "tieu dem.json. Symptoms of nocturia\nA normal person can sleep 6-8 hours, without waking up in the middle of the night to urinate. People with nocturia will wake up more than once during sleep to urinate. If this condition lasts long, it can make the patient feel tired or even physically weak. When the cause comes from a disease, if you delay treatment, you can face dangerous complications from the disease."
}