{
    "document_name": "viem-duong-tiet-nieu-sau-sinh.json",
    "document_name_accent": "viem duong tiet nieu sau sinh.json",
    "document_title": "Postpartum urinary tract infection: Causes and effective treatments",
    "document_category": "Obstetrics - Gynecology ",
    "subsection_name": "viem-duong-tiet-nieu-sau-sinh.json_3_Diagnosis of postpartum urinary tract infection",
    "subsection_content": "Before giving a treatment regimen for postpartum urinary tract infections, the specialist will prescribe the pregnant woman some tests and diagnostic imaging as follows:\nUrine sample analysis: Taking a urine sample will help your doctor find white blood cells, red blood cells or bacteria to determine your infection.; Bacterial culture in the laboratory: This test shows the type of bacteria that is causing your infection to decide on the right medication.; Imaging diagnosis: Through ultrasound, computed tomography (CT), and magnetic resonance imaging (MRI), the doctor will examine the urinary tract to find structural abnormalities; Endoscopy: If you have frequent UTIs, your doctor may perform a cystoscopy to check and evaluate the infection or take tissue and urine samples for further investigation.",
    "subsection_title": "viem duong tiet nieu sau sinh.json. Diagnosis of postpartum urinary tract infection",
    "subsection_data": "viem duong tiet nieu sau sinh.json. Diagnosis of postpartum urinary tract infection\nBefore giving a treatment regimen for postpartum urinary tract infections, the specialist will prescribe the pregnant woman some tests and diagnostic imaging as follows:\nUrine sample analysis: Taking a urine sample will help your doctor find white blood cells, red blood cells or bacteria to determine your infection.; Bacterial culture in the laboratory: This test shows the type of bacteria that is causing your infection to decide on the right medication.; Imaging diagnosis: Through ultrasound, computed tomography (CT), and magnetic resonance imaging (MRI), the doctor will examine the urinary tract to find structural abnormalities; Endoscopy: If you have frequent UTIs, your doctor may perform a cystoscopy to check and evaluate the infection or take tissue and urine samples for further investigation."
}