{
    "document_name": "mun-trung-ca-o-lung",
    "document_name_accent": "Mụn trứng cá ở lưng",
    "document_title": "Mụn trứng cá ở lưng: Nguyên nhân, triệu chứng, cách phòng ngừa",
    "document_category": "Da liễu",
    "subsection_name": "mun-trung-ca-o-lung_2_Nổi mụn trứng cá ở lưng có nguy hiểm không?",
    "subsection_content": "Tuy chỉ là vấn đề ngoài da, ít có nguy hiểm tới sức khỏe nhưng về mặt sinh hoạt hằng ngày mụn lưng sẽ có ảnh hưởng không nhỏ.\nCó ảnh hưởng đến sinh hoạt thường ngày không?\nSo với mụn trứng cá ở mặt, mụn trứng cá ở lưng cũng có ảnh hưởng không nhỏ tới sinh hoạt thường nhật. Không chỉ gây mất thẩm mỹ như để lại các vết sưng đỏ, thâm mụn, sẹo mụn mà mụn ở lưng có thể gây ngứa ngáy, khó chịu, đau nhức,… khi nằm hoặc ma sát vào trang phục/ đồ đạc.\nỞ mức độ nghiêm trọng hơn, mụn cũng có nguy cơ gây nhiễm trùng da khiến thời gian điều trị phải kéo dài, gây nhiều bất tiện trong sinh hoạt.\nMụn trứng cá ở lưng gây ngứa ngáy, đau nhức ảnh hưởng không nhỏ tới sinh hoạt",
    "subsection_title": "Mụn trứng cá ở lưng. Nổi mụn trứng cá ở lưng có nguy hiểm không?",
    "subsection_data": "Mụn trứng cá ở lưng. Nổi mụn trứng cá ở lưng có nguy hiểm không?\nTuy chỉ là vấn đề ngoài da, ít có nguy hiểm tới sức khỏe nhưng về mặt sinh hoạt hằng ngày mụn lưng sẽ có ảnh hưởng không nhỏ.\nCó ảnh hưởng đến sinh hoạt thường ngày không?\nSo với mụn trứng cá ở mặt, mụn trứng cá ở lưng cũng có ảnh hưởng không nhỏ tới sinh hoạt thường nhật. Không chỉ gây mất thẩm mỹ như để lại các vết sưng đỏ, thâm mụn, sẹo mụn mà mụn ở lưng có thể gây ngứa ngáy, khó chịu, đau nhức,… khi nằm hoặc ma sát vào trang phục/ đồ đạc.\nỞ mức độ nghiêm trọng hơn, mụn cũng có nguy cơ gây nhiễm trùng da khiến thời gian điều trị phải kéo dài, gây nhiều bất tiện trong sinh hoạt.\nMụn trứng cá ở lưng gây ngứa ngáy, đau nhức ảnh hưởng không nhỏ tới sinh hoạt"
}