{
    "document_name": "ung-thu-vu-giai-doan-dau",
    "document_name_accent": "Ung thư vú giai đoạn đầu",
    "document_title": "Ung thư vú giai đoạn đầu (sớm): Triệu chứng, chẩn đoán và điều trị",
    "document_category": "Ung bướu",
    "subsection_name": "ung-thu-vu-giai-doan-dau_6_Tác dụng phụ của các phương pháp điều trị ung thư vú",
    "subsection_content": "Bất kỳ phương pháp điều trị nào cũng có nguy cơ xảy ra các biến chứng hay tác dụng phụ không mong muốn.\nCác biến chứng phẫu thuật bao gồm: Nhiễm trùng, đau đớn, chảy máu, vấn đề thẩm mỹ, sẹo vĩnh viễn, thay đổi hoặc mất cảm giác ở vùng ngực và ngực được tái tạo.; Các tác dụng phụ của hóa trị bao gồm: Buồn nôn/nôn mửa và tiêu chảy, rụng tóc, mất trí nhớ, khô âm đạo, các triệu chứng mãn kinh, vấn đề sinh sản, bệnh thần kinh.; Các tác dụng phụ đi kèm với liệu pháp nội tiết bao gồm: Nóng bừng, khô âm đạo tiết dịch, mệt mỏi, buồn nôn.; Xạ trị có thể gây ra các tác dụng phụ sau: Đau và thay đổi da, mệt mỏi, buồn nôn, rụng tóc, các vấn đề về tim và phổi (dài hạn), bệnh thần kinh.\nNgười bệnh có thể gặp phải các tác dụng phụ trong và sau quá trình điều trị như rụng tóc, nôn ói, mệt mỏi…\nUng thư vú là bệnh ung thư phổ biến nhất được chẩn đoán ở phụ nữ, chiếm hơn 1/10 trường hợp ung thư mới được chẩn đoán mỗi năm. Đây là nguyên nhân phổ biến thứ hai gây tử vong do ung thư ở phụ nữ trên thế giới. Ung thư vú ở phụ nữ xảy ra ở mọi lứa tuổi sau tuổi dậy thì nhưng tỷ lệ sẽ tăng lên khi tuổi càng lớn dần. Theo thống kê của Globocan năm 2020, Việt Nam có 21.555 ca mắc mới ung thư vú, chiếm đến 25,8% tổng các loại ung thư ở phụ nữ, trong đó có hơn 9.345 trường hợp tử vong vì căn bệnh này.\nĐể đặt lịch khám, tầm soát và điều trị ung thư vú tại Bệnh viện Đa khoa Tâm Anh, Quý khách vui lòng liên hệ:\nBác sĩ Khiêm khuyên, điều trị ung thư vú giai đoạn đầu thường mang đến kết quả tốt với tỷ lệ sống gần như 100%. Do đó việc phát hiện sớm ung thư vú là tiền đề để tốt nhất cho việc điều trị. Phụ nữ nên thường xuyên kiểm tra vú để phát hiện sự thay đổi trên da, trong mô vú. Nên thăm khám sức khỏe định kỳ mỗi 6 tháng một lần và đến ngay bệnh viện khi nhận thấy bất kỳ dấu hiệu nào nghi ngờ.",
    "subsection_title": "Ung thư vú giai đoạn đầu. Tác dụng phụ của các phương pháp điều trị ung thư vú",
    "subsection_data": "Ung thư vú giai đoạn đầu. Tác dụng phụ của các phương pháp điều trị ung thư vú\nBất kỳ phương pháp điều trị nào cũng có nguy cơ xảy ra các biến chứng hay tác dụng phụ không mong muốn.\nCác biến chứng phẫu thuật bao gồm: Nhiễm trùng, đau đớn, chảy máu, vấn đề thẩm mỹ, sẹo vĩnh viễn, thay đổi hoặc mất cảm giác ở vùng ngực và ngực được tái tạo.; Các tác dụng phụ của hóa trị bao gồm: Buồn nôn/nôn mửa và tiêu chảy, rụng tóc, mất trí nhớ, khô âm đạo, các triệu chứng mãn kinh, vấn đề sinh sản, bệnh thần kinh.; Các tác dụng phụ đi kèm với liệu pháp nội tiết bao gồm: Nóng bừng, khô âm đạo tiết dịch, mệt mỏi, buồn nôn.; Xạ trị có thể gây ra các tác dụng phụ sau: Đau và thay đổi da, mệt mỏi, buồn nôn, rụng tóc, các vấn đề về tim và phổi (dài hạn), bệnh thần kinh.\nNgười bệnh có thể gặp phải các tác dụng phụ trong và sau quá trình điều trị như rụng tóc, nôn ói, mệt mỏi…\nUng thư vú là bệnh ung thư phổ biến nhất được chẩn đoán ở phụ nữ, chiếm hơn 1/10 trường hợp ung thư mới được chẩn đoán mỗi năm. Đây là nguyên nhân phổ biến thứ hai gây tử vong do ung thư ở phụ nữ trên thế giới. Ung thư vú ở phụ nữ xảy ra ở mọi lứa tuổi sau tuổi dậy thì nhưng tỷ lệ sẽ tăng lên khi tuổi càng lớn dần. Theo thống kê của Globocan năm 2020, Việt Nam có 21.555 ca mắc mới ung thư vú, chiếm đến 25,8% tổng các loại ung thư ở phụ nữ, trong đó có hơn 9.345 trường hợp tử vong vì căn bệnh này.\nĐể đặt lịch khám, tầm soát và điều trị ung thư vú tại Bệnh viện Đa khoa Tâm Anh, Quý khách vui lòng liên hệ:\nBác sĩ Khiêm khuyên, điều trị ung thư vú giai đoạn đầu thường mang đến kết quả tốt với tỷ lệ sống gần như 100%. Do đó việc phát hiện sớm ung thư vú là tiền đề để tốt nhất cho việc điều trị. Phụ nữ nên thường xuyên kiểm tra vú để phát hiện sự thay đổi trên da, trong mô vú. Nên thăm khám sức khỏe định kỳ mỗi 6 tháng một lần và đến ngay bệnh viện khi nhận thấy bất kỳ dấu hiệu nào nghi ngờ."
}