{
    "document_name": "viem-hong-hat",
    "document_name_accent": "Viêm họng hạt",
    "document_title": "Viêm họng hạt: Nguyên nhân, dấu hiệu, cách phòng ngừa và điều trị",
    "document_category": "Tai mũi họng",
    "subsection_name": "viem-hong-hat_1_Nguyên nhân gây viêm họng hạt",
    "subsection_content": "Bệnh viêm họng hạt có thể do nhiều nguyên nhân gây ra, bao gồm:\nSự tấn công của các tác nhân gây hại: Khoang miệng là nơi thường xuyên tiếp xúc với các loại virus, vi khuẩn hoặc nấm gây bệnh. Khi có điều kiện thuận lợi, chúng sẽ tấn công, gây viêm nhiễm. Thông thường, virus sẽ tấn công trước, sau đó vi khuẩn và nấm tiếp tục xâm nhập theo, gây bội nhiễm. Điều này khiến các tế bào lympho tại vùng họng phải làm việc liên tục, quá tải và sưng to.; Sự tấn công của các tác nhân gây hại: Khoang miệng là nơi thường xuyên tiếp xúc với các loại virus, vi khuẩn hoặc nấm gây bệnh. Khi có điều kiện thuận lợi, chúng sẽ tấn công, gây viêm nhiễm. Thông thường, virus sẽ tấn công trước, sau đó vi khuẩn và nấm tiếp tục xâm nhập theo, gây bội nhiễm. Điều này khiến các tế bào lympho tại vùng họng phải làm việc liên tục, quá tải và sưng to.\nBiến chứng bệnh lý: Viêm họng hạt có thể là biến chứng của viêm mũi xoang mạn tính, viêm họng cấp tái phát nhiều lần, viêm amidan mạn tính hoặc các bệnh đường tiêu hóa như trào ngược họng thanh quản,…; Biến chứng bệnh lý: Viêm họng hạt có thể là biến chứng của viêm mũi xoang mạn tính, viêm họng cấp tái phát nhiều lần, viêm amidan mạn tính hoặc các bệnh đường tiêu hóa như trào ngược họng thanh quản,…\nBất thường trong giải phẫu cấu trúc mũi xoang: polyp mũi, lệch vẹo vách ngăn,; Bất thường trong giải phẫu cấu trúc mũi xoang: polyp mũi, lệch vẹo vách ngăn,\nMôi trường sống ô nhiễm: Việc thường xuyên tiếp xúc với hóa chất độc hại, khói bụi, khói thuốc lá… hoặc thời tiết thất thường cũng là những yếu tố nguy cơ.; Môi trường sống ô nhiễm: Việc thường xuyên tiếp xúc với hóa chất độc hại, khói bụi, khói thuốc lá… hoặc thời tiết thất thường cũng là những yếu tố nguy cơ.\nLối sống không lành mạnh: Lạm dụng rượu bia, đồ ăn cay nóng, vệ sinh răng miệng kém… cũng góp phần kích thích cổ họng và tạo điều kiện để các tác nhân xấu xâm nhập, gây viêm nhiễm.; Lối sống không lành mạnh: Lạm dụng rượu bia, đồ ăn cay nóng, vệ sinh răng miệng kém… cũng góp phần kích thích cổ họng và tạo điều kiện để các tác nhân xấu xâm nhập, gây viêm nhiễm.\nYếu tố cơ địa, di truyền: các yếu tố cơ địa nhạy cảm, một số bệnh di truyền, miễn dịch cũng là nguyên nhân làm tăng nguy cơ bị viêm họng hạt.; Yếu tố cơ địa, di truyền: các yếu tố cơ địa nhạy cảm, một số bệnh di truyền, miễn dịch cũng là nguyên nhân làm tăng nguy cơ bị viêm họng hạt.",
    "subsection_title": "Viêm họng hạt. Nguyên nhân gây viêm họng hạt",
    "subsection_data": "Viêm họng hạt. Nguyên nhân gây viêm họng hạt\nBệnh viêm họng hạt có thể do nhiều nguyên nhân gây ra, bao gồm:\nSự tấn công của các tác nhân gây hại: Khoang miệng là nơi thường xuyên tiếp xúc với các loại virus, vi khuẩn hoặc nấm gây bệnh. Khi có điều kiện thuận lợi, chúng sẽ tấn công, gây viêm nhiễm. Thông thường, virus sẽ tấn công trước, sau đó vi khuẩn và nấm tiếp tục xâm nhập theo, gây bội nhiễm. Điều này khiến các tế bào lympho tại vùng họng phải làm việc liên tục, quá tải và sưng to.; Sự tấn công của các tác nhân gây hại: Khoang miệng là nơi thường xuyên tiếp xúc với các loại virus, vi khuẩn hoặc nấm gây bệnh. Khi có điều kiện thuận lợi, chúng sẽ tấn công, gây viêm nhiễm. Thông thường, virus sẽ tấn công trước, sau đó vi khuẩn và nấm tiếp tục xâm nhập theo, gây bội nhiễm. Điều này khiến các tế bào lympho tại vùng họng phải làm việc liên tục, quá tải và sưng to.\nBiến chứng bệnh lý: Viêm họng hạt có thể là biến chứng của viêm mũi xoang mạn tính, viêm họng cấp tái phát nhiều lần, viêm amidan mạn tính hoặc các bệnh đường tiêu hóa như trào ngược họng thanh quản,…; Biến chứng bệnh lý: Viêm họng hạt có thể là biến chứng của viêm mũi xoang mạn tính, viêm họng cấp tái phát nhiều lần, viêm amidan mạn tính hoặc các bệnh đường tiêu hóa như trào ngược họng thanh quản,…\nBất thường trong giải phẫu cấu trúc mũi xoang: polyp mũi, lệch vẹo vách ngăn,; Bất thường trong giải phẫu cấu trúc mũi xoang: polyp mũi, lệch vẹo vách ngăn,\nMôi trường sống ô nhiễm: Việc thường xuyên tiếp xúc với hóa chất độc hại, khói bụi, khói thuốc lá… hoặc thời tiết thất thường cũng là những yếu tố nguy cơ.; Môi trường sống ô nhiễm: Việc thường xuyên tiếp xúc với hóa chất độc hại, khói bụi, khói thuốc lá… hoặc thời tiết thất thường cũng là những yếu tố nguy cơ.\nLối sống không lành mạnh: Lạm dụng rượu bia, đồ ăn cay nóng, vệ sinh răng miệng kém… cũng góp phần kích thích cổ họng và tạo điều kiện để các tác nhân xấu xâm nhập, gây viêm nhiễm.; Lối sống không lành mạnh: Lạm dụng rượu bia, đồ ăn cay nóng, vệ sinh răng miệng kém… cũng góp phần kích thích cổ họng và tạo điều kiện để các tác nhân xấu xâm nhập, gây viêm nhiễm.\nYếu tố cơ địa, di truyền: các yếu tố cơ địa nhạy cảm, một số bệnh di truyền, miễn dịch cũng là nguyên nhân làm tăng nguy cơ bị viêm họng hạt.; Yếu tố cơ địa, di truyền: các yếu tố cơ địa nhạy cảm, một số bệnh di truyền, miễn dịch cũng là nguyên nhân làm tăng nguy cơ bị viêm họng hạt."
}